PyMiniGPT/Readme.md
PyMiniGPT/__init__.py
PyMiniGPT/binjiefun.py
PyMiniGPT/blackb.py
PyMiniGPT/duckgo.py
PyMiniGPT/powerbrainai.py
pyminigpt-0.1.0.dist-info/WHEEL
pyminigpt-0.1.0.dist-info/METADATA
pyminigpt-0.1.0.dist-info/RECORD
