Metadata-Version: 2.3
Name: PyMiniGPT
Version: 0.1.0
Summary: A small GPT model
Keywords: gpt,mini,ai
Author-email: SPARK <sparkisbackbro@gmail.com>
